claude_skills_mcp/__init__.py
claude_skills_mcp/__main__.py
claude_skills_mcp/backend_manager.py
claude_skills_mcp/mcp_proxy.py
claude_skills_mcp-1.0.6.dist-info/METADATA
claude_skills_mcp-1.0.6.dist-info/WHEEL
claude_skills_mcp-1.0.6.dist-info/entry_points.txt
claude_skills_mcp-1.0.6.dist-info/RECORD
