Metadata-Version: 2.4
Name: claude-skills-mcp
Version: 1.0.6
Summary: Lightweight MCP proxy for Claude Skills (auto-downloads backend)
Project-URL: Homepage, https://github.com/K-Dense-AI/claude-skills-mcp
Project-URL: Documentation, https://github.com/K-Dense-AI/claude-skills-mcp/blob/main/README.md
Project-URL: Repository, https://github.com/K-Dense-AI/claude-skills-mcp
Project-URL: Bug Tracker, https://github.com/K-Dense-AI/claude-skills-mcp/issues
Project-URL: Backend, https://pypi.org/project/claude-skills-mcp-backend/
Author-email: K-Dense AI <orion.li@k-dense.ai>
Maintainer-email: K-Dense AI <orion.li@k-dense.ai>
License: Apache-2.0
Keywords: agent,ai,claude,mcp,proxy,skills
Classifier: Development Status :: 4 - Beta
Classifier: Intended Audience :: Developers
Classifier: Intended Audience :: Science/Research
Classifier: License :: OSI Approved :: Apache Software License
Classifier: Programming Language :: Python :: 3.12
Classifier: Topic :: Scientific/Engineering :: Artificial Intelligence
Requires-Python: <3.13,>=3.12
Requires-Dist: httpx>=0.24.0
Requires-Dist: mcp>=1.0.0
Provides-Extra: test
Requires-Dist: pytest-asyncio>=0.21.0; extra == 'test'
Requires-Dist: pytest>=7.4.0; extra == 'test'
